<?xml version="1.0" encoding="utf-8"?><Zestimate:zestimate xmlns:xsi="http://www.w3.org/2001/XMLSchema-instance" xmlns:Zestimate="http://www.zillow.com/static/xsd/Zestimate.xsd" xsi:schemaLocation="http://www.zillow.com/static/xsd/Zestimate.xsd http://www.zillowstatic.com/vstatic/LATEST/static/xsd/Zestimate.xsd"><request><zpid>15089347</zpid></request><message><text>Request successfully processed</text><code>0</code></message><response><zpid>15089347</zpid><links><homedetails>http://www.zillow.com/homedetails/33-5th-Ave-San-Francisco-CA-94118/15089347_zpid/</homedetails><graphsanddata>http://www.zillow.com/homedetails/33-5th-Ave-San-Francisco-CA-94118/15089347_zpid/#charts-and-data</graphsanddata><mapthishome>http://www.zillow.com/homes/15089347_zpid/</mapthishome><comparables>http://www.zillow.com/homes/comps/15089347_zpid/</comparables></links><address><street>33 5th Ave</street><zipcode>94118</zipcode><city>San Francisco</city><state>CA</state><latitude>37.788078</latitude><longitude>-122.464048</longitude></address><zestimate><amount currency="USD">4192618</amount><last-updated>03/30/2014</last-updated><oneWeekChange deprecated="true"></oneWeekChange><valueChange duration="30" currency="USD">66262</valueChange><valuationRange><low currency="USD">3815282</low><high currency="USD">4528027</high></valuationRange><percentile>93</percentile></zestimate><localRealEstate><region id="256657" type="neighborhood" name="Lake"><links><overview>http://www.zillow.com/local-info/CA-San-Francisco/Lake/r_256657/</overview><forSaleByOwner>http://www.zillow.com/lake-san-francisco-ca/fsbo/</forSaleByOwner><forSale>http://www.zillow.com/lake-san-francisco-ca/</forSale></links></region></localRealEstate><regions><zipcode-id>97572</zipcode-id><city-id>20330</city-id><county-id>3227</county-id><state-id>9</state-id></regions></response></Zestimate:zestimate><!-- H:003  T:8ms  S:878  R:Tue Apr 01 17:38:33 PDT 2014  B:3.0.223790.20140331104204299-comp_rel_a.223790.20140331104438306-comp_rel_a -->